personal-verilog/myself/lemming_2.v
module lemming_2(
    input clk,bump_left,bump_right,areset,ground,
    output reg walk_left,
    output reg walk_right,aaah
);

reg dum;
reg fall;

always@(posedge clk, posedge areset)begin
    if(areset)begin
        aaah=1'b0;
        fall=1'b0;
        walk_left=1'b1;
        walk_right=~walk_left;
        dum=walk_left;end
    
    else begin
        if(ground)begin
            aaah=1'b0;
            walk_left=dum;
            walk_right=~dum;   
            if(walk_left)begin
                walk_left=(bump_left)?(fall)?walk_left:~walk_left:walk_left;
                fall=1'b0;
                walk_right=~walk_left;end
            
            else if(walk_right)begin
                walk_right=(bump_right)?(fall)?walk_right:~walk_right:walk_right;
                fall=1'b0;
                walk_left=~walk_right;end
                
            dum=walk_left;end
        else begin
            fall=1'b1;
            walk_left=1'b0;
            walk_right=1'b0;
            aaah=1'b1;
        end
    end
end
endmodule

personal-verilog/myself/lemming_2_tb.v
module lemming_2_tb;
    reg CLK=1,BUMP_LEFT=0,BUMP_RIGHT=0,ARESET=1,GROUND=1;
    wire WALK_LEFT,WALK_RIGHT,AAAH;

    always#1
        CLK=~CLK;

    initial begin
        #3 ARESET=~ARESET;end

    initial begin
        #12 BUMP_LEFT=~BUMP_LEFT;
        #4 BUMP_LEFT=~BUMP_LEFT;end

    /*initial begin
        #24 BUMP_RIGHT=~BUMP_RIGHT;end*/

    initial begin
        #7 GROUND=~GROUND;
        #5 GROUND=~GROUND;
        #4 GROUND=~GROUND;
        #6 GROUND=~GROUND;end

    lemming_2 uut(
        .clk(CLK),
        .bump_left(BUMP_LEFT),
        .bump_right(BUMP_RIGHT),
        .areset(ARESET),
        .ground(GROUND),
        .walk_left(WALK_LEFT),
        .walk_right(WALK_RIGHT),
        .aaah(AAAH)
    );

    initial begin
        $dumpfile("lemming_2.vcd");
        $dumpvars(0,lemming_2_tb);        
        #50 $finish;
    end

endmodule

verilog/myself/lemming_2.vcd
$date
	Sun Aug 18 09:12:34 2024
$end
$version
	Icarus Verilog
$end
$timescale
	1s
$end
$scope module lemming_2_tb $end
$var wire 1 ! WALK_RIGHT $end
$var wire 1 " WALK_LEFT $end
$var wire 1 # AAAH $end
$var reg 1 $ ARESET $end
$var reg 1 % BUMP_LEFT $end
$var reg 1 & BUMP_RIGHT $end
$var reg 1 ' CLK $end
$var reg 1 ( GROUND $end
$scope module uut $end
$var wire 1 $ areset $end
$var wire 1 % bump_left $end
$var wire 1 & bump_right $end
$var wire 1 ' clk $end
$var wire 1 ( ground $end
$var reg 1 # aaah $end
$var reg 1 ) dum $end
$var reg 1 * fall $end
$var reg 1 " walk_left $end
$var reg 1 ! walk_right $end
$upscope $end
$upscope $end
$enddefinitions $end
$comment Show the parameter values. $end
$dumpall
$end
#0
$dumpvars
0*
1)
1(
1'
0&
0%
1$
0#
1"
0!
$end
#1
0'
#2
1'
#3
0'
0$
#4
1'
#5
0'
#6
1'
#7
0'
0(
#8
1#
0"
1*
1'
#9
0'
#10
1'
#11
0'
#12
0*
1"
0#
1'
1(
1%
#13
0'
#14
0)
1!
0"
1'
#15
0'
#16
1#
0!
1*
1'
0(
0%
#17
0'
#18
1'
#19
0'
#20
1'
#21
0'
#22
0*
1!
0#
1'
1(
