verilog/myself/pipo.v
module pipo(
    input clk,load,
    input[7:0]d_in,
    output reg[3:0]q
);

reg[7:0]d;

initial
    d=8'd0;

always@(posedge clk)begin
    if(load)
        d=d_in;
    d=d>>1;
    q<=d[3:0];
end


endmodule

personal-verilog/myself/pipo_tb.v
module pipo_tb;
    reg CLK=0,LOAD=1;
    reg[7:0]D_IN=8'b11010000;
    wire[3:0] Q;

    pipo uut_1(
        .clk(CLK),
        .load(LOAD),
        .d_in(D_IN),
        .q(Q)
    );

    always#2
        CLK=~CLK;

    initial
    #5 LOAD=0;

    initial
        begin
            $dumpfile("pipo.vcd");
            $dumpvars(0,pipo_tb);

            $monitor("%g %d %d",$time,D_IN,Q);
            #40 $finish;
        end

endmodule

verilog/myself/pipo.vcd
$date
	Sun Jul 21 20:43:10 2024
$end
$version
	Icarus Verilog
$end
$timescale
	1s
$end
$scope module pipo_tb $end
$var wire 4 ! Q [3:0] $end
$var reg 1 " CLK $end
$var reg 8 # D_IN [7:0] $end
$var reg 1 $ LOAD $end
$scope module uut_1 $end
$var wire 1 " clk $end
$var wire 8 % d_in [7:0] $end
$var wire 1 $ load $end
$var reg 8 & d [7:0] $end
$var reg 4 ' q [3:0] $end
$upscope $end
$upscope $end
$enddefinitions $end
$comment Show the parameter values. $end
$dumpall
$end
#0
$dumpvars
bx '
b0 &
b11010000 %
1$
b11010000 #
0"
bx !
$end
#2
b1000 !
b1000 '
b1101000 &
1"
#4
0"
#5
0$
#6
b100 !
b100 '
b110100 &
1"
#8
0"
#10
b1010 !
b1010 '
b11010 &
1"
#12
0"
#14
b1101 !
b1101 '
b1101 &
1"
#16
0"
#18
b110 !
b110 '
b110 &
1"
#20
0"
#22
b11 !
b11 '
b11 &
1"
#24
0"
#26
b1 !
b1 '
b1 &
1"
#28
0"
#30
b0 !
b0 '
b0 &
1"
