personal-verilog/myself/own/sample_1.v
module sample_1(s,c0,a,b,c);
    output s,c0;
    input a,b,c;
    wire w1,w2,w3;
    xor(s,a,b,c);
    and(w1,a,b);
    and(w2,c,b);
    and(w3,a,c);
    or(c0,w1,w2,w3);
endmodule

personal-verilog/myself/own/sample_1_tb.v
module sample_1_tb;

//inputs
    reg a;
    reg b;
    reg c;

//outputs
    wire s;
    wire c0;

//instantiation
    sample_1 uut (
    .s(s),
    .c0(c0),
    .a(a),
    .b(b),
    .c(c)
    );

initial
    begin
        $dumpfile("sample_1.vcd");
        $dumpvars(0,sample_1_tb);

            {a,b,c}=3'b000;
         #2 {a,b,c}=3'b001;
         #2 {a,b,c}=3'b010;
         #2 {a,b,c}=3'b011;
         #2 {a,b,c}=3'b100;
         #2 {a,b,c}=3'b101;
         #2 {a,b,c}=3'b110;
         #2 {a,b,c}=3'b111;
    end

initial $monitor ("time=%g, a=%b, b=%b, c=%b, c0=%b, s=%b", $time,a,b,c,c0,s);

initial #20 $finish;

endmodule

verilog/myself/own/sample_1.vcd
$date
	Tue Apr 23 13:51:13 2024
$end
$version
	Icarus Verilog
$end
$timescale
	1s
$end
$scope module sample_1_tb $end
$var wire 1 ! s $end
$var wire 1 " c0 $end
$var reg 1 # a $end
$var reg 1 $ b $end
$var reg 1 % c $end
$scope module uut $end
$var wire 1 # a $end
$var wire 1 $ b $end
$var wire 1 % c $end
$var wire 1 " c0 $end
$var wire 1 ! s $end
$var wire 1 & w1 $end
$var wire 1 ' w2 $end
$var wire 1 ( w3 $end
$upscope $end
$upscope $end
$enddefinitions $end
$comment Show the parameter values. $end
$dumpall
$end
#0
$dumpvars
0(
0'
0&
0%
0$
0#
0"
0!
$end
#2
1!
1%
#4
1$
0%
#6
1"
0!
1'
1%
#8
0"
1!
0'
1#
0$
0%
#10
1"
0!
1(
1%
#12
1&
0(
1$
0%
#14
1!
1'
1(
1%
