verilog/ds/booth.v
module BoothMultiplier (
    input wire clk,
    input wire reset,
    input wire start,
    input wire signed [7:0] multiplicand,
    input wire signed [7:0] multiplier,
    output reg signed [15:0] product,
    output reg done
);

    reg [2:0] state;
    reg signed [7:0] A;
    reg signed [15:0] Q;
    reg Q_minus_1;
    reg [3:0] count;

    parameter IDLE = 3'd0, LOAD = 3'd1, PROCESS = 3'd2, SHIFT = 3'd3, DONE = 3'd4;

    always @(posedge clk or posedge reset) begin
        if (reset) begin
            state <= IDLE;
            done <= 0;
        end else begin
            case (state)
                IDLE: begin
                    done <= 0;
                    if (start) begin
                        state <= LOAD;
                    end
                end
                LOAD: begin
                    A <= multiplicand;
                    Q <= {8'b0, multiplier};
                    Q_minus_1 <= 0;
                    count <= 8;
                    state <= PROCESS;
                end
                PROCESS: begin
                    case ({Q[0], Q_minus_1})
                        2'b01: Q[15:8] <= Q[15:8] + A;
                        2'b10: Q[15:8] <= Q[15:8] - A;
                    endcase
                    state <= SHIFT;
                end
                SHIFT: begin
                    Q <= {Q[15], Q[15:1]};
                    Q_minus_1 <= Q[0];
                    count <= count - 1;
                    if (count == 0)
                        state <= DONE;
                    else
                        state <= PROCESS;
                end
                DONE: begin
                    product <= Q;
                    done <= 1;
                    state <= IDLE;
                end
            endcase
        end
    end
endmodule

personal-verilog/ds/booth_tb.v
`timescale 1ns / 1ps
module testBoothMultiplier;
    reg clk;
    reg reset;
    reg start;
    reg signed [7:0] multiplicand;
    reg signed [7:0] multiplier;
    wire signed [15:0] product;
    wire done;

    BoothMultiplier uut (
        .clk(clk),
        .reset(reset),
        .start(start),
        .multiplicand(multiplicand),
        .multiplier(multiplier),
        .product(product),
        .done(done)
    );

    // Clock generation
    initial begin
        $dumpfile ("booth.vcd");
        $dumpvars(0,testBoothMultiplier);
        clk = 0;
        forever #10 clk = ~clk;
    end

    // Test vectors
    initial begin
        reset = 1; start = 0; #25;
        reset = 0;

        // Test case 1: Positive numbers
        multiplicand = 8'd15; // 15
        multiplier = 8'd10;   // 10
        start = 1;
        #20 start = 0;
        wait(done);
        $display("Test Case 1: (%d) * (%d) = %d", multiplicand, multiplier, product);

        #30;
        reset = 1; #20; reset = 0; // Reset between tests

        // Test case 2: Negative and positive mix
        multiplicand = -8'd20; // -20
        multiplier = 8'd25;    // 25
        start = 1;
        #20 start = 0;
        wait(done);
        $display("Test Case 2: (%d) * (%d) = %d", multiplicand, multiplier, product);

        #30;
        reset = 1; #20; reset = 0;

        // Test case 3: Both numbers negative
        multiplicand = -8'd17; // -17
        multiplier = -8'd11;   // -11
        start = 1;
        #20 start = 0;
        wait(done);
        $display("Test Case 3: (%d) * (%d) = %d", multiplicand, multiplier, product);

        #100;
        $finish;
    end
endmodule

personal-verilog/ds/booth.vcd
$date
	Mon Apr 22 05:34:58 2024
$end
$version
	Icarus Verilog
$end
$timescale
	1ps
$end
$scope module testBoothMultiplier $end
$var wire 16 ! product [15:0] $end
$var wire 1 " done $end
$var reg 1 # clk $end
$var reg 8 $ multiplicand [7:0] $end
$var reg 8 % multiplier [7:0] $end
$var reg 1 & reset $end
$var reg 1 ' start $end
$scope module uut $end
$var wire 1 # clk $end
$var wire 8 ( multiplicand [7:0] $end
$var wire 8 ) multiplier [7:0] $end
$var wire 1 & reset $end
$var wire 1 ' start $end
$var parameter 3 * DONE $end
$var parameter 3 + IDLE $end
$var parameter 3 , LOAD $end
$var parameter 3 - PROCESS $end
$var parameter 3 . SHIFT $end
$var reg 8 / A [7:0] $end
$var reg 16 0 Q [15:0] $end
$var reg 1 1 Q_minus_1 $end
$var reg 4 2 count [3:0] $end
$var reg 1 " done $end
$var reg 16 3 product [15:0] $end
$var reg 3 4 state [2:0] $end
$upscope $end
$upscope $end
$enddefinitions $end
$comment Show the parameter values. $end
$dumpall
b11 .
b10 -
b1 ,
b0 +
b100 *
$end
#0
$dumpvars
b0 4
bx 3
bx 2
x1
bx 0
bx /
bx )
bx (
0'
1&
bx %
bx $
0#
0"
bx !
$end
#10000
1#
#20000
0#
#25000
1'
b1010 %
b1010 )
b1111 $
b1111 (
0&
#30000
b1 4
1#
#40000
0#
#45000
0'
#50000
b10 4
b1000 2
01
b1010 0
b1111 /
1#
#60000
0#
#70000
b11 4
1#
#80000
0#
#90000
b10 4
b111 2
b101 0
1#
#100000
0#
#110000
b11 4
b1111000100000101 0
1#
#120000
0#
#130000
b10 4
b110 2
11
b1111100010000010 0
1#
#140000
0#
#150000
b11 4
b11110000010 0
1#
#160000
0#
#170000
b10 4
b101 2
01
b1111000001 0
1#
#180000
0#
#190000
b11 4
b1111010011000001 0
1#
#200000
0#
#210000
b10 4
b100 2
11
b1111101001100000 0
1#
#220000
0#
#230000
b11 4
b100101100000 0
1#
#240000
0#
#250000
b10 4
b11 2
01
b10010110000 0
1#
#260000
0#
#270000
b11 4
1#
#280000
0#
#290000
b10 4
b10 2
b1001011000 0
1#
#300000
0#
#310000
b11 4
1#
#320000
0#
#330000
b10 4
b1 2
b100101100 0
1#
#340000
0#
#350000
b11 4
1#
#360000
0#
#370000
b10 4
b0 2
b10010110 0
1#
#380000
0#
#390000
b11 4
1#
#400000
0#
#410000
b100 4
b1111 2
b1001011 0
1#
#420000
0#
#430000
b0 4
1"
b1001011 !
b1001011 3
1#
#440000
0#
#450000
0"
1#
#460000
0#
1&
#470000
1#
#480000
0#
1'
b11001 %
b11001 )
b11101100 $
b11101100 (
0&
#490000
b1 4
1#
#500000
0#
0'
#510000
b10 4
b1000 2
b11001 0
b11101100 /
1#
#520000
0#
#530000
b11 4
b1010000011001 0
1#
#540000
0#
#550000
b10 4
b111 2
11
b101000001100 0
1#
#560000
0#
#570000
b11 4
b1111011000001100 0
1#
#580000
0#
#590000
b10 4
b110 2
01
b1111101100000110 0
1#
#600000
0#
#610000
b11 4
1#
#620000
0#
#630000
b10 4
b101 2
b1111110110000011 0
1#
#640000
0#
#650000
b11 4
b1000110000011 0
1#
#660000
0#
#670000
b10 4
b100 2
11
b100011000001 0
1#
#680000
0#
#690000
b11 4
1#
#700000
0#
#710000
b10 4
b11 2
b10001100000 0
1#
#720000
0#
#730000
b11 4
b1111000001100000 0
1#
#740000
0#
#750000
b10 4
b10 2
01
b1111100000110000 0
1#
#760000
0#
#770000
b11 4
1#
#780000
0#
#790000
b10 4
b1 2
b1111110000011000 0
1#
#800000
0#
#810000
b11 4
1#
#820000
0#
#830000
b10 4
b0 2
b1111111000001100 0
1#
#840000
0#
#850000
b11 4
1#
#860000
0#
#870000
b100 4
b1111 2
b1111111100000110 0
1#
#880000
0#
#890000
b0 4
1"
b1111111100000110 !
b1111111100000110 3
1#
#900000
0#
#910000
0"
1#
#920000
0#
1&
#930000
1#
#940000
0#
1'
b11110101 %
b11110101 )
b11101111 $
b11101111 (
0&
#950000
b1 4
1#
#960000
0#
0'
#970000
b10 4
b1000 2
b11110101 0
b11101111 /
1#
#980000
0#
#990000
b11 4
b1000111110101 0
1#
#1000000
0#
#1010000
b10 4
b111 2
11
b100011111010 0
1#
#1020000
0#
#1030000
b11 4
b1111011111111010 0
1#
#1040000
0#
#1050000
b10 4
b110 2
01
b1111101111111101 0
1#
#1060000
0#
#1070000
b11 4
b110011111101 0
1#
#1080000
0#
#1090000
b10 4
b101 2
11
b11001111110 0
1#
#1100000
0#
#1110000
b11 4
b1111010101111110 0
1#
#1120000
0#
#1130000
b10 4
b100 2
01
b1111101010111111 0
1#
#1140000
0#
#1150000
b11 4
b101110111111 0
1#
#1160000
0#
#1170000
b10 4
b11 2
11
b10111011111 0
1#
#1180000
0#
#1190000
b11 4
1#
#1200000
0#
#1210000
b10 4
b10 2
b1011101111 0
1#
#1220000
0#
#1230000
b11 4
1#
#1240000
0#
#1250000
b10 4
b1 2
b101110111 0
1#
#1260000
0#
#1270000
b11 4
1#
#1280000
0#
#1290000
b10 4
b0 2
b10111011 0
1#
#1300000
0#
#1310000
b11 4
1#
#1320000
0#
#1330000
b100 4
b1111 2
b1011101 0
1#
#1340000
0#
#1350000
b0 4
1"
b1011101 !
b1011101 3
1#
#1360000
0#
#1370000
0"
1#
