personal-verilog/ds/fulladder_str.v
module fulladder_str(output s,c0, input a,b,c);
    wire t1,t2,k;
    xor (s,a,b,c);
    xor (k,a,b);
    and(t1,a,b);
    and(t2,k,c);
    or(c0,t1,t2);
endmodule

verilog/ds/fulladder_str_tb.v
module fulladder_tb;

//inputs
    reg a;
    reg b;
    reg c;

//outputs
    wire s;
    wire c0;

//instantiate the UUT
    fulladder_str uut(
        .s(s),
        .c0(c0),
        .a(a),
        .b(b),
        .c(c)
    );

    initial
        begin
            $dumpfile("fulladder.vcd");
            $dumpvars(0,fulladder_tb);

                {a,b,c}=3'b000;
            #2  {a,b,c}=3'b001;
            #2  {a,b,c}=3'b010;
            #2  {a,b,c}=3'b011;
            #2  {a,b,c}=3'b100;
            #2  {a,b,c}=3'b101;
            #2  {a,b,c}=3'b110;
            #2  {a,b,c}=3'b111;
        end

    initial $monitor("time=%g, c0=%b, s=%b, a=%b, b=%b, c=%b", $time,c0,s,a,b,c);
    initial #20 $finish;

endmodule

personal-verilog/ds/fulladder.vcd
$date
	Tue Apr 23 13:08:15 2024
$end
$version
	Icarus Verilog
$end
$timescale
	1s
$end
$scope module fulladder_tb $end
$var wire 1 ! s $end
$var wire 1 " c0 $end
$var reg 1 # a $end
$var reg 1 $ b $end
$var reg 1 % c $end
$scope module uut $end
$var wire 1 # a $end
$var wire 1 $ b $end
$var wire 1 % c $end
$var wire 1 " c0 $end
$var wire 1 & k $end
$var wire 1 ! s $end
$var wire 1 ' t1 $end
$var wire 1 ( t2 $end
$upscope $end
$upscope $end
$enddefinitions $end
$comment Show the parameter values. $end
$dumpall
$end
#0
$dumpvars
0(
0'
0&
0%
0$
0#
0"
0!
$end
#2
1!
1%
#4
1&
1$
0%
#6
1"
0!
1(
1%
#8
0"
1!
0(
1#
0$
0%
#10
1"
0!
1(
1%
#12
0&
1'
0(
1$
0%
#14
1!
1%
