personal-verilog/myself/clock.v
module clock(input wire clk);

endmodule

personal-verilog/myself/clock_tb.v
module clock_tb;

    reg clock=1;
    reg[2:0] d;
    reg[2:0] q;
    clock dut(.clk(clock));
    
    always#(2)
        begin
            clock=~clock;
        end

    always@(posedge clock)
        begin
            q<=d;
        end

    initial
        begin
            $dumpfile("clock.vcd");
            $dumpvars(0,clock_tb);
                d=3'd00;
            #2  d=3'd01;
            #2  d=3'd02;
            #2  d=3'd03;
            #2  d=3'd04;
            #2  d=3'd05;
            #2  d=3'd06;
            #2  d=3'd07;

            $monitor("%b %b %b",d,q,clock,$time);
            #2 $finish;
        end
endmodule

personal-verilog/myself/clock.vcd
$date
	Tue Jul 09 11:15:46 2024
$end
$version
	Icarus Verilog
$end
$timescale
	1s
$end
$scope module clock_tb $end
$var reg 1 ! clock $end
$var reg 3 " d [2:0] $end
$var reg 3 # q [2:0] $end
$scope module dut $end
$var wire 1 ! clk $end
$upscope $end
$upscope $end
$enddefinitions $end
$comment Show the parameter values. $end
$dumpall
$end
#0
$dumpvars
bx #
b0 "
1!
$end
#2
b1 "
0!
#4
b10 #
b10 "
1!
#6
b11 "
0!
#8
b100 #
b100 "
1!
#10
b101 "
0!
#12
b110 #
b110 "
1!
#14
b111 "
0!
#16
b111 #
1!
