verilog/myself/fa_csw.v
module cswap(p,q,r,m,n,o);

input p,q,r;
output m,n,o;

assign m=p;
assign n=(p&r)|(~p&q);
assign o=(p&q)|(~p&r);

endmodule

module full_adder(a,b,c_in,c_out,s);

input a,b,c_in;
output s,c_out;

wire x,y,z;

cswap uut_2(
    .p(a),
    .q(b),
    .r(c_in),
    .m(x),
    .n(y),
    .o(z)
);

assign c_out=(x&y)|(y&z)|(z&x);
assign s=x&~(y^z)|(~x&(y^z));

endmodule

verilog/myself/fa_csw_tb.v
module fa_tb;
    reg A,B,C;
    wire S,C_O;

    full_adder uut_1(
        .a(A),
        .b(B),
        .c_in(C),
        .c_out(C_O),
        .s(S)
    );

    integer i;

    initial
        begin
            $dumpfile("fa_csw.vcd");
            $dumpvars(0,fa_tb);
            
            for(i=0;i<8;i++)
                #5 {A,B,C}=i;

            $monitor("%g %b %b %b %b %b",$time,A,B,C,C_O,S);
            #5 $finish;
        end

endmodule

personal-verilog/myself/fa_csw.vcd
$date
	Fri Jul 19 19:19:45 2024
$end
$version
	Icarus Verilog
$end
$timescale
	1s
$end
$scope module fa_tb $end
$var wire 1 ! S $end
$var wire 1 " C_O $end
$var reg 1 # A $end
$var reg 1 $ B $end
$var reg 1 % C $end
$var integer 32 & i [31:0] $end
$scope module uut_1 $end
$var wire 1 # a $end
$var wire 1 $ b $end
$var wire 1 % c_in $end
$var wire 1 " c_out $end
$var wire 1 ! s $end
$var wire 1 ' z $end
$var wire 1 ( y $end
$var wire 1 ) x $end
$scope module uut_2 $end
$var wire 1 ) m $end
$var wire 1 ( n $end
$var wire 1 ' o $end
$var wire 1 # p $end
$var wire 1 $ q $end
$var wire 1 % r $end
$upscope $end
$upscope $end
$upscope $end
$enddefinitions $end
$comment Show the parameter values. $end
$dumpall
$end
#0
$dumpvars
x)
x(
x'
b0 &
x%
x$
x#
x"
x!
$end
#5
0!
0"
0(
0'
b1 &
0)
0#
0$
0%
#10
1!
1'
b10 &
1%
#15
1(
0'
b11 &
1$
0%
#20
0!
1"
1'
b100 &
1%
#25
0"
1!
0(
0'
b101 &
1)
1#
0$
0%
#30
0!
1"
1(
b110 &
1%
#35
1'
0(
b111 &
1$
0%
#40
1!
1(
b1000 &
1%
