verilog/myself/lemming_1.v
module lemming_1(
    input clk,bump_left,bump_right,areset,
    output reg walk_left,
    output reg walk_right
);
reg dum;
always@(posedge clk, posedge areset)begin
    if(areset)begin
        walk_left=1'b1;
        walk_right=~walk_left;
        dum=walk_left;end
    
    else begin
        walk_left=dum;
        walk_right=~dum;   
        if(walk_left)begin
            walk_left=(bump_left)?~walk_left:walk_left;
            walk_right=~walk_left;end
        
        else if(walk_right)begin
            walk_right=(bump_right)?~walk_right:walk_right;
            walk_left=~walk_right;end

        dum=walk_left;
    end
end
endmodule

personal-verilog/myself/lemming_1_tb.v
module lemming_1_tb;
    reg CLK=0,BUMP_LEFT=1,BUMP_RIGHT=1,ARESET=1;
    wire WALK_LEFT,WALK_RIGHT;

    always#1
        CLK=~CLK;

    initial begin
        #3 ARESET=~ARESET;
        #8 ARESET=~ARESET;
        #3 ARESET=~ARESET;end

    initial begin
        #20 BUMP_LEFT=~BUMP_LEFT;
        #4 BUMP_LEFT=~BUMP_LEFT;end

    initial begin
        #24 BUMP_RIGHT=~BUMP_RIGHT;end

    lemming_1 uut(
        .clk(CLK),
        .bump_left(BUMP_LEFT),
        .bump_right(BUMP_RIGHT),
        .areset(ARESET),
        .walk_left(WALK_LEFT),
        .walk_right(WALK_RIGHT)
    );

    initial begin
        $dumpfile("lemming_1.vcd");
        $dumpvars(0,lemming_1_tb);        
        #50 $finish;
    end

endmodule

personal-verilog/myself/lemming_1.vcd
$date
	Sun Aug 18 04:41:49 2024
$end
$version
	Icarus Verilog
$end
$timescale
	1s
$end
$scope module lemming_1_tb $end
$var wire 1 ! WALK_RIGHT $end
$var wire 1 " WALK_LEFT $end
$var reg 1 # ARESET $end
$var reg 1 $ BUMP_LEFT $end
$var reg 1 % BUMP_RIGHT $end
$var reg 1 & CLK $end
$scope module uut $end
$var wire 1 # areset $end
$var wire 1 $ bump_left $end
$var wire 1 % bump_right $end
$var wire 1 & clk $end
$var reg 1 ' dum $end
$var reg 1 " walk_left $end
$var reg 1 ! walk_right $end
$upscope $end
$upscope $end
$enddefinitions $end
$comment Show the parameter values. $end
$dumpall
$end
#0
$dumpvars
1'
0&
1%
1$
1#
1"
0!
$end
#1
1&
#2
0&
#3
0'
1!
0"
1&
0#
#4
0&
#5
1'
1"
0!
1&
#6
0&
#7
0'
1!
0"
1&
#8
0&
#9
1'
1"
0!
1&
#10
0&
#11
1&
1#
#12
0&
#13
1&
#14
0&
0#
#15
0'
1!
0"
1&
#16
0&
#17
1'
1"
0!
1&
#18
0&
#19
0'
1!
0"
1&
#20
0&
0$
#21
1'
1"
0!
1&
#22
0&
#23
1&
#24
0&
1$
0%
#25
0'
1!
0"
1&
