personal-verilog/myself/piso.v
module piso(
    input clk,load,
    input[3:0]d_in,
    output reg q
);

reg[3:0] d;

initial
d=4'b0;

always@(posedge clk)begin
    if(load)
        d=d_in;
    q<=d[0];
    d=d>>1;
end


endmodule

verilog/myself/piso_tb.v
module piso_tb;
    reg CLK=0,LOAD=1;
    reg[3:0] D_IN=4'b1101;
    wire Q;

    piso uut_1(
        .clk(CLK),
        .load(LOAD),
        .d_in(D_IN),
        .q(Q)
    );

    always#1
        CLK=~CLK;

    initial
    #3 LOAD=0;

    always#11 begin
        LOAD=~LOAD;
        #3 LOAD=~LOAD;end

    integer i;

    initial
        begin
            $dumpfile("piso.vcd");
            $dumpvars(0,piso_tb);
                for(i=0;i<15;i++)
                    #11 D_IN=i;
            $monitor("%g %b",$time,Q);
            #20 $finish;
        end


endmodule

personal-verilog/myself/piso.vcd
$date
	Sun Jul 21 21:05:29 2024
$end
$version
	Icarus Verilog
$end
$timescale
	1s
$end
$scope module piso_tb $end
$var wire 1 ! Q $end
$var reg 1 " CLK $end
$var reg 4 # D_IN [3:0] $end
$var reg 1 $ LOAD $end
$var integer 32 % i [31:0] $end
$scope module uut_1 $end
$var wire 1 " clk $end
$var wire 4 & d_in [3:0] $end
$var wire 1 $ load $end
$var reg 4 ' d [3:0] $end
$var reg 1 ! q $end
$upscope $end
$upscope $end
$enddefinitions $end
$comment Show the parameter values. $end
$dumpall
$end
#0
$dumpvars
b0 '
b1101 &
b0 %
1$
b1101 #
0"
x!
$end
#1
0!
b1101 '
1"
#2
0"
#3
1!
b110 '
1"
0$
#4
0"
#5
0!
b11 '
1"
#6
0"
#7
1!
b1 '
1"
#8
0"
#9
b0 '
1"
#10
0"
#11
0!
1"
b1 %
b0 #
b0 &
1$
#12
0"
#13
1"
#14
0"
0$
#15
1"
#16
0"
#17
1"
#18
0"
#19
1"
#20
0"
#21
1"
#22
0"
b10 %
b1 #
b1 &
#23
1"
#24
0"
#25
b1 '
1"
1$
#26
0"
#27
1"
#28
0"
0$
#29
1!
b0 '
1"
#30
0"
#31
0!
1"
#32
0"
#33
1"
b11 %
b10 #
b10 &
#34
0"
#35
1"
#36
0"
#37
1"
#38
0"
#39
b10 '
1"
1$
#40
0"
#41
1"
#42
0"
0$
#43
b1 '
1"
#44
0"
b100 %
b11 #
b11 &
#45
1!
b0 '
1"
#46
0"
#47
0!
1"
#48
0"
#49
1"
#50
0"
#51
1"
#52
0"
#53
b11 '
1"
1$
#54
0"
#55
b100 '
1"
b101 %
b100 #
b100 &
#56
0"
0$
#57
b10 '
1"
#58
0"
#59
b1 '
1"
#60
0"
#61
1!
b0 '
1"
#62
0"
#63
0!
1"
#64
0"
#65
1"
#66
0"
b110 %
b101 #
b101 &
#67
b101 '
1"
1$
#68
0"
#69
1"
#70
0"
0$
#71
1!
b10 '
1"
#72
0"
#73
0!
b1 '
1"
#74
0"
#75
1!
b0 '
1"
#76
0"
#77
0!
1"
b111 %
b110 #
b110 &
#78
0"
#79
1"
#80
0"
#81
b110 '
1"
1$
#82
0"
#83
1"
#84
0"
0$
#85
b11 '
1"
#86
0"
#87
1!
b1 '
1"
#88
0"
b1000 %
b111 #
b111 &
#89
b0 '
1"
#90
0"
#91
0!
1"
#92
0"
#93
1"
#94
0"
#95
b111 '
1"
1$
#96
0"
#97
1"
#98
0"
0$
#99
1!
b11 '
1"
b1001 %
b1000 #
b1000 &
#100
0"
#101
b1 '
1"
#102
0"
#103
b0 '
1"
#104
0"
#105
0!
1"
#106
0"
#107
1"
#108
0"
#109
b1000 '
1"
1$
#110
0"
b1010 %
b1001 #
b1001 &
#111
b1001 '
1"
#112
0"
0$
#113
1!
b100 '
1"
#114
0"
#115
0!
b10 '
1"
#116
0"
#117
b1 '
1"
#118
0"
#119
1!
b0 '
1"
#120
0"
#121
0!
1"
b1011 %
b1010 #
b1010 &
#122
0"
#123
b1010 '
1"
1$
#124
0"
#125
1"
#126
0"
0$
#127
b101 '
1"
#128
0"
#129
1!
b10 '
1"
#130
0"
#131
0!
b1 '
1"
#132
0"
b1100 %
b1011 #
b1011 &
#133
1!
b0 '
1"
#134
0"
#135
0!
1"
#136
0"
#137
b1011 '
1"
1$
#138
0"
#139
1"
#140
0"
0$
#141
1!
b101 '
1"
#142
0"
#143
b10 '
1"
b1101 %
b1100 #
b1100 &
#144
0"
#145
0!
b1 '
1"
#146
0"
#147
1!
b0 '
1"
#148
0"
#149
0!
1"
#150
0"
#151
b1100 '
1"
1$
#152
0"
#153
1"
#154
0"
0$
b1110 %
b1101 #
b1101 &
#155
b110 '
1"
#156
0"
#157
b11 '
1"
#158
0"
#159
1!
b1 '
1"
#160
0"
#161
b0 '
1"
#162
0"
#163
0!
1"
#164
0"
#165
b1110 '
1"
1$
b1111 %
b1110 #
b1110 &
#166
0"
#167
1"
#168
0"
0$
#169
b111 '
1"
#170
0"
#171
1!
b11 '
1"
#172
0"
#173
b1 '
1"
#174
0"
#175
b0 '
1"
#176
0"
#177
0!
1"
#178
0"
#179
b1110 '
1"
1$
#180
0"
#181
1"
#182
0"
0$
#183
b111 '
1"
#184
0"
#185
1!
b11 '
1"
