personal-verilog/myself/own/d_ff.v
module d_ff (
    input wire clk,
    input wire reset,
    input wire d,
    output reg q
);

always@(posedge clk or posedge reset)
    begin
        if (reset)
            q<=1'b0;
        else
            q<=d;
    end

endmodule

personal-verilog/myself/own/d_ff_tb.v
module d_ff_tb;
//inputs
reg clk=0, d=0, reset=0;
//outputs
wire q;
//parameter
parameter period = 10;
//intsantiate
d_ff dut(
    .clk(clk),
    .reset(reset),
    .d(d),
    .q(q)
);

always #(period/2) clk = ~clk;

initial
    begin
        $dumpfile("d_ff.vcd");
        $dumpvars(0,d_ff_tb);
        $monitor("time = %g, d=%b, q=%b",$time,d,q);
        #20 reset =1;
        #10 reset =0;
        #50 d=1;
        #20 d=0;
        #100 $finish;
    end

endmodule

personal-verilog/myself/own/d_ff.vcd
$date
	Thu Apr 25 05:51:00 2024
$end
$version
	Icarus Verilog
$end
$timescale
	1s
$end
$scope module d_ff_tb $end
$var wire 1 ! q $end
$var parameter 32 " period $end
$var reg 1 # clk $end
$var reg 1 $ d $end
$var reg 1 % reset $end
$scope module dut $end
$var wire 1 # clk $end
$var wire 1 $ d $end
$var wire 1 % reset $end
$var reg 1 ! q $end
$upscope $end
$upscope $end
$enddefinitions $end
$comment Show the parameter values. $end
$dumpall
b1010 "
$end
#0
$dumpvars
0%
0$
0#
x!
$end
#5
0!
1#
#10
0#
#15
1#
#20
0#
1%
#25
1#
#30
0#
0%
#35
1#
#40
0#
#45
1#
#50
0#
#55
1#
#60
0#
#65
1#
#70
0#
#75
1#
#80
0#
1$
#85
1!
1#
#90
0#
#95
1#
#100
0#
0$
#105
0!
1#
