personal-verilog/myself/own/sample_1_behave.v
module sample_1_behave(o,a,b,c);
    output reg o;
    input a,b,c;
    always@(*)
        begin
            o=(a|b)&c;
        end
endmodule

personal-verilog/myself/own/sample_1_behave_tb.v
module sample_1_behave_tb;

//outputs
    wire o;

//inputs 
    reg a,b,c;

//instantiation
    sample_1_behave uut(
        .a(a),
        .b(b),
        .c(c),
        .o(o)
    );

initial
    begin
        $dumpfile("sample_1_behave.vcd");
        $dumpvars(0,sample_1_behave_tb);
            {a,b,c}=3'b000;
          #1{a,b,c}=3'b001;
          #1{a,b,c}=3'b010;
          #1{a,b,c}=3'b011;
          #1{a,b,c}=3'b100;
          #1{a,b,c}=3'b101;
          #1{a,b,c}=3'b110;
          #1{a,b,c}=3'b111;
    end

initial $monitor("time=%gns, a=%b, b=%b, c=%b, o=%b",$time,a,b,c,o);

initial #10 $finish;

endmodule

personal-verilog/myself/own/sample_1_behave.vcd
$date
	Wed Apr 24 10:15:32 2024
$end
$version
	Icarus Verilog
$end
$timescale
	1s
$end
$scope module sample_1_behave_tb $end
$var wire 1 ! o $end
$var reg 1 " a $end
$var reg 1 # b $end
$var reg 1 $ c $end
$scope module uut $end
$var wire 1 " a $end
$var wire 1 # b $end
$var wire 1 $ c $end
$var reg 1 ! o $end
$upscope $end
$upscope $end
$enddefinitions $end
$comment Show the parameter values. $end
$dumpall
$end
#0
$dumpvars
0$
0#
0"
0!
$end
#1
1$
#2
1#
0$
#3
1!
1$
#4
0!
1"
0#
0$
#5
1!
1$
#6
0!
1#
0$
#7
1!
1$
