personal-verilog/myself/own/sample.v
module sample(a,b,c,o);
    input a,b,c;
    output o;
    wire w;
    or (w,a,b);
    and (o,w,c);
endmodule

personal-verilog/ds/sample_tb.v
module sample_tb;

reg a,b,c;
wire o;

sample uut(
    .a(a),
    .b(b),
    .c(c),
    .o(o)

);

initial
    begin
        $dumpfile("sample.vcd");
        $dumpvars(0,sample_tb);
            {a,b,c}=3'b000;
        #2  {a,b,c}=3'b001;
        #2  {a,b,c}=3'b010;
        #2  {a,b,c}=3'b011;
        #2  {a,b,c}=3'b100;
        #2  {a,b,c}=3'b101;
        #2  {a,b,c}=3'b110;
        #2  {a,b,c}=3'b111;
    end

initial $monitor("time=%g, a=%b, b=%b, c=%b",$time,a,b,c);
initial #20 $finish;

endmodule

personal-verilog/myself/own/sample.vcd
$date
	Tue Apr 23 15:45:16 2024
$end
$version
	Icarus Verilog
$end
$timescale
	1s
$end
$scope module sample_tb $end
$var wire 1 ! o $end
$var reg 1 " a $end
$var reg 1 # b $end
$var reg 1 $ c $end
$scope module uut $end
$var wire 1 " a $end
$var wire 1 # b $end
$var wire 1 $ c $end
$var wire 1 ! o $end
$var wire 1 % w $end
$upscope $end
$upscope $end
$enddefinitions $end
$comment Show the parameter values. $end
$dumpall
$end
#0
$dumpvars
0%
0$
0#
0"
0!
$end
#2
1$
#4
1%
1#
0$
#6
1!
1$
#8
0!
1"
0#
0$
#10
1!
1$
#12
0!
1#
0$
#14
1!
1$
